rodrigogoncalves_json2csv_pucminas/converter.py
rodrigogoncalves_json2csv_pucminas-0.1.0.dist-info/entry_points.txt
rodrigogoncalves_json2csv_pucminas-0.1.0.dist-info/WHEEL
rodrigogoncalves_json2csv_pucminas-0.1.0.dist-info/METADATA
rodrigogoncalves_json2csv_pucminas-0.1.0.dist-info/RECORD
