Metadata-Version: 2.1
Name: rodrigogoncalves-json2csv-pucminas
Version: 0.1.0
Summary: Converter Csv2Json for learning purposes
Author: Rodrigo Pereira Gonçalves
Author-email: rodrigo.goncalves@engenharia.ufjf.br
Requires-Python: >=3.8,<4.0
Classifier: Programming Language :: Python :: 3
Classifier: Programming Language :: Python :: 3.10
Classifier: Programming Language :: Python :: 3.8
Classifier: Programming Language :: Python :: 3.9
Requires-Dist: click (>=8.0.3,<9.0.0)
Requires-Dist: pandas (>=1.3.4,<2.0.0)
